{
  "global/variables": {
    "colors": {
      "neutral": {
        "0": {
          "value": "#ffffff",
          "type": "color"
        },
        "50": {
          "value": "#eceef5",
          "type": "color"
        },
        "100": {
          "value": "#d4d8e4",
          "type": "color"
        },
        "200": {
          "value": "#bfc3cf",
          "type": "color"
        },
        "300": {
          "value": "#a5a9b5",
          "type": "color"
        },
        "400": {
          "value": "#979aa3",
          "type": "color"
        },
        "500": {
          "value": "#81848e",
          "type": "color"
        },
        "600": {
          "value": "#757881",
          "type": "color"
        },
        "700": {
          "value": "#555963",
          "type": "color"
        },
        "800": {
          "value": "#3d404a",
          "type": "color"
        },
        "900": {
          "value": "#20232b",
          "type": "color"
        },
        "950": {
          "value": "#111319",
          "type": "color"
        }
      },
      "blue": {
        "50": {
          "value": "#eff6ff",
          "type": "color"
        },
        "100": {
          "value": "#dbeafe",
          "type": "color"
        },
        "200": {
          "value": "#bfdbfe",
          "type": "color"
        },
        "300": {
          "value": "#93c5fd",
          "type": "color"
        },
        "400": {
          "value": "#60a5fa",
          "type": "color"
        },
        "500": {
          "value": "#3071fb",
          "type": "color"
        },
        "600": {
          "value": "#0048e3",
          "type": "color"
        },
        "700": {
          "value": "#1d4ed8",
          "type": "color"
        },
        "800": {
          "value": "#1e40af",
          "type": "color"
        },
        "900": {
          "value": "#1e3a8a",
          "type": "color"
        },
        "950": {
          "value": "#172554",
          "type": "color"
        }
      },
      "white": {
        "100%": {
          "value": "#ffffff",
          "type": "color"
        },
        "90%": {
          "value": "#ffffffe6",
          "type": "color"
        },
        "80%": {
          "value": "#ffffffcc",
          "type": "color"
        },
        "70%": {
          "value": "#ffffffb3",
          "type": "color"
        },
        "60%": {
          "value": "#ffffff99",
          "type": "color"
        },
        "50%": {
          "value": "#ffffff80",
          "type": "color"
        },
        "40%": {
          "value": "#ffffff66",
          "type": "color"
        },
        "30%": {
          "value": "#ffffff4d",
          "type": "color"
        },
        "20%": {
          "value": "#ffffff33",
          "type": "color"
        },
        "10%": {
          "value": "#ffffff1a",
          "type": "color"
        },
        "0%": {
          "value": "#ffffff00",
          "type": "color"
        }
      }
    },
    "font-family": {
      "default": {
        "value": "Mulish",
        "type": "text"
      },
      "code": {
        "value": "Mulish",
        "type": "text"
      }
    },
    "spacing": {
      "1": {
        "value": 4,
        "type": "number"
      },
      "2": {
        "value": 8,
        "type": "number"
      },
      "3": {
        "value": 12,
        "type": "number"
      },
      "4": {
        "value": 16,
        "type": "number"
      },
      "5": {
        "value": 20,
        "type": "number"
      },
      "6": {
        "value": 24,
        "type": "number"
      },
      "8": {
        "value": 32,
        "type": "number"
      },
      "10": {
        "value": 40,
        "type": "number"
      },
      "13": {
        "value": 52,
        "type": "number"
      },
      "16": {
        "value": 64,
        "type": "number"
      },
      "0'5": {
        "value": 2,
        "type": "number"
      },
      "1'5": {
        "value": 6,
        "type": "number"
      },
      "2'5": {
        "value": 10,
        "type": "number"
      },
      "3'5": {
        "value": 14,
        "type": "number"
      }
    },
    "radius": {
      "sm": {
        "value": 4,
        "type": "number"
      },
      "lg": {
        "value": 12,
        "type": "number"
      },
      "xl": {
        "value": 20,
        "type": "number"
      },
      "2xl": {
        "value": 32,
        "type": "number"
      },
      "md": {
        "value": 8,
        "type": "number"
      },
      "xs": {
        "value": 2,
        "type": "number"
      },
      "none": {
        "value": 0,
        "type": "number"
      },
      "full": {
        "value": 999,
        "type": "number"
      }
    },
    "font-size": {
      "3xs": {
        "value": 10,
        "type": "number"
      },
      "2xs": {
        "value": 11,
        "type": "number"
      },
      "xs": {
        "value": 12,
        "type": "number"
      },
      "sm": {
        "value": 13,
        "type": "number"
      },
      "md": {
        "value": 14,
        "type": "number"
      },
      "lg": {
        "value": 16,
        "type": "number"
      },
      "xl": {
        "value": 20,
        "type": "number"
      }
    },
    "line-height": {
      "3xs": {
        "value": 14,
        "type": "number"
      },
      "2xs": {
        "value": 15,
        "type": "number"
      },
      "xs": {
        "value": 16,
        "type": "number"
      },
      "sm": {
        "value": 18,
        "type": "number"
      },
      "md": {
        "value": 20,
        "type": "number"
      },
      "lg": {
        "value": 24,
        "type": "number"
      },
      "xl": {
        "value": 26,
        "type": "number"
      }
    }
  },
  "theme-colors/light": {
    "text": {
      "body": {
        "value": "{colors.neutral.950}",
        "type": "color"
      },
      "muted": {
        "value": "{colors.neutral.600}",
        "type": "color"
      },
      "extramuted": {
        "value": "{colors.neutral.500}",
        "type": "color"
      },
      "primary": {
        "value": "{colors.blue.600}",
        "type": "color"
      }
    },
    "background": {
      "default": {
        "value": "{colors.neutral.0}",
        "type": "color"
      },
      "muted": {
        "value": "{colors.neutral.50}",
        "type": "color"
      },
      "bg-primary": {
        "value": "{colors.blue.600}",
        "type": "color"
      },
      "bg-primary-subtle": {
        "value": "{colors.blue.100}",
        "type": "color"
      },
      "bg-danger": {
        "value": "{colors.blue.600}",
        "type": "color"
      },
      "bg-danger-subtle": {
        "value": "{colors.blue.100}",
        "type": "color"
      }
    }
  },
  "theme-colors/dark": {
    "text": {
      "body": {
        "value": "{colors.neutral.50}",
        "type": "color"
      },
      "muted": {
        "value": "{colors.neutral.200}",
        "type": "color"
      },
      "extramuted": {
        "value": "{colors.neutral.400}",
        "type": "color"
      },
      "primary": {
        "value": "{colors.blue.500}",
        "type": "color"
      }
    },
    "background": {
      "default": {
        "value": "{colors.neutral.900}",
        "type": "color"
      },
      "muted": {
        "value": "{colors.neutral.950}",
        "type": "color"
      },
      "bg-primary": {
        "value": "{colors.blue.500}",
        "type": "color"
      },
      "bg-primary-subtle": {
        "value": "{colors.blue.950}",
        "type": "color"
      },
      "bg-danger": {
        "value": "{colors.blue.500}",
        "type": "color"
      },
      "bg-danger-subtle": {
        "value": "{colors.blue.950}",
        "type": "color"
      }
    }
  },
  "input/xs": {
    "input-size": {
      "value": 26,
      "type": "number"
    },
    "input-radius": {
      "value": "{radius.xs}",
      "type": "number"
    },
    "input-x-padding": {
      "value": "{spacing.2}",
      "type": "number"
    },
    "input-x-gap": {
      "value": "{spacing.1}",
      "type": "number"
    },
    "input-text-size": {
      "value": "{font-size.xs}",
      "type": "number"
    },
    "input-line-height": {
      "value": "{line-height.xs}",
      "type": "number"
    }
  },
  "input/sm": {
    "input-size": {
      "value": 34,
      "type": "number"
    },
    "input-radius": {
      "value": "{radius.sm}",
      "type": "number"
    },
    "input-x-padding": {
      "value": "{spacing.3}",
      "type": "number"
    },
    "input-x-gap": {
      "value": "{spacing.2}",
      "type": "number"
    },
    "input-text-size": {
      "value": "{font-size.sm}",
      "type": "number"
    },
    "input-line-height": {
      "value": "{line-height.sm}",
      "type": "number"
    }
  },
  "input/md": {
    "input-size": {
      "value": 42,
      "type": "number"
    },
    "input-radius": {
      "value": "{radius.md}",
      "type": "number"
    },
    "input-x-padding": {
      "value": "{spacing.4}",
      "type": "number"
    },
    "input-x-gap": {
      "value": "{spacing.3}",
      "type": "number"
    },
    "input-text-size": {
      "value": "{font-size.md}",
      "type": "number"
    },
    "input-line-height": {
      "value": "{line-height.md}",
      "type": "number"
    }
  },
  "input/lg": {
    "input-size": {
      "value": 48,
      "type": "number"
    },
    "input-radius": {
      "value": "{radius.lg}",
      "type": "number"
    },
    "input-x-padding": {
      "value": "{spacing.5}",
      "type": "number"
    },
    "input-x-gap": {
      "value": "{spacing.4}",
      "type": "number"
    },
    "input-text-size": {
      "value": "{font-size.lg}",
      "type": "number"
    },
    "input-line-height": {
      "value": "{line-height.lg}",
      "type": "number"
    }
  },
  "$themes": [
    {
      "id": "global-variables",
      "name": "variables",
      "group": "global",
      "selectedTokenSets": {
        "global/variables": "enabled"
      },
      "$figmaStyleReferences": {},
      "$figmaVariableReferences": {
        "colors.neutral.0": "d19a57905ece8420afa2b61696ca2279a9b721cb",
        "colors.neutral.50": "8c3325a471f6cb2f2802b7d2196c574bfe39f9e8",
        "colors.neutral.100": "22aaa74f6972e8d5e82a6eff8f5d088b5d58f682",
        "colors.neutral.200": "a2939113603d2d64c28855991361bdee87f3abeb",
        "colors.neutral.300": "aaf204d6b345dd3858e4bab485201ae4020a0965",
        "colors.neutral.400": "c2cf243894e02f98f941d12408a4b00a0310ea28",
        "colors.neutral.500": "7738969d36b30d7a799ad61039157f7b7b2751ba",
        "colors.neutral.600": "a8e9b0f9e1d8bc9894db68aadd4cf353930f62c3",
        "colors.neutral.700": "2590675bbf59b44db4dd0f79578e091a54250650",
        "colors.neutral.800": "2c7dfbff37db43b1e2cc3198b3ef1eee74184f7d",
        "colors.neutral.900": "738072656c785fe9beb38d6c2aa91447958f4a29",
        "colors.neutral.950": "c0e8a98dd6592c94744e7ed04e802bb7e411d8a2",
        "colors.blue.50": "dd5932855e1f5bb102c252469a9c666d6134fe6b",
        "colors.blue.100": "27fb507ae0f923c7788a690a64225e20f95667c4",
        "colors.blue.200": "0c9fcbd290188a34b14c4595ac4294fad77105b0",
        "colors.blue.300": "de21c99de3ac6b2044f63984ee28ef5edc86a331",
        "colors.blue.400": "e3c7de00da639a45b238695b3435fc486e93d66d",
        "colors.blue.500": "be364190c643716f91fd45c750f9fd89cccc4e7b",
        "colors.blue.600": "d141b2e0518e1d333975659f3dbe90d5344eb772",
        "colors.blue.700": "35b648b8f4c849631e05f00d8c94f2a6f06891c4",
        "colors.blue.800": "d5d4e3c5a8c7f8a69b7e513c7aa9de3b1365f937",
        "colors.blue.900": "31afd785fb108b5e623684855da0401509794e32",
        "colors.blue.950": "b7bb370ec3c4e3f127ec263bb84ed9cc80b6395f",
        "colors.white.100%": "c503d2597630c40d15b3855bca3eabeac5a70ec8",
        "colors.white.90%": "0e93ea10b4b54627e291bd1f9ea8fabf722b23b9",
        "colors.white.80%": "6711a374f09c5747ff6538e8a92f026a4df55790",
        "colors.white.70%": "083fda15487254ae7e7edc4c39c650098edfd29d",
        "colors.white.60%": "0abfe909a1257871f566600278a8dbfe8cf17343",
        "colors.white.50%": "8c43ed17598b4dd0cb3a24851bdfcff86eecfaf2",
        "colors.white.40%": "27c8a02104bb136a818beab5e3fdc8d4d4b51672",
        "colors.white.30%": "5f2278b0899728b427081e99909dffcc2b7e518b",
        "colors.white.20%": "aaeca70bc9ef272819834a8cf7e70ef960129095",
        "colors.white.10%": "3ba9373b067507731efc259e880d40a0a5dfb026",
        "colors.white.0%": "3fe883ae629f32024f6d12e54a2d971ce0014bbc",
        "font-family.default": "1469de1bfa754fbdc4c740cbb2a2baa179252511",
        "font-family.code": "f32d0fa482a6bb805195f81e50008aefc649b92e",
        "spacing.1": "57931b724626acfe4f1d283033ca52600a288bf7",
        "spacing.2": "41b831d2a9f3836644ef859886114ce810659b62",
        "spacing.3": "305ba9e10d617e114a1d23a130a0fa1b1c433dd0",
        "spacing.4": "c25718fd3f6923bf885d16b2361366eeb91407ec",
        "spacing.5": "043e717723f8d9ff3a0472563f032dc52a4ce9f6",
        "spacing.6": "f016aabe3dd02999a4ba88a490fe26ee52246f0a",
        "spacing.8": "2ffb82ce4f46a913edc3932027e4698e5359cb41",
        "spacing.10": "60c32dfe1a0df61ff476b11bc19ed1d7745e8547",
        "spacing.13": "19820b3f7eb67c3100d5d095aa9c99e0da9254dd",
        "spacing.16": "921fdd68941c32c47e0e68f3168651db479fc141",
        "spacing.0'5": "461614f3d54d0dc296183b1b87041a05c0281553",
        "spacing.1'5": "ffe1784ea921856f966936b33793156a31562ad9",
        "spacing.2'5": "904b2b92225a4ecb125b41e5825601dc5a291af5",
        "spacing.3'5": "3d414a8bd42210c7f29a0ea9b93727b9a54fa208",
        "radius.sm": "609fa5d0639d70f1d7e35e9b96ce5f246da53fab",
        "radius.lg": "9cae72568636f158484370df7e516e51dcfdab77",
        "radius.xl": "ccfce46f2acf4aeea610889017af46d9857c939e",
        "radius.2xl": "db1b1298c6b89e51548a813e12ea1580c75d2f86",
        "radius.md": "c233b8a283d1e81eb71fd5398ac13c6bff1db007",
        "radius.xs": "8b783baa0f7eea09cdf9947e4f4eb6324fed404a",
        "radius.none": "19669dd471d85b289a80e89731d5562462ce3973",
        "radius.full": "9512c87c7a32b20232a47ccdf059b9a105e69ab8",
        "font-size.3xs": "191a8c11b11988dd7655331b2aa02465f277000d",
        "font-size.2xs": "1d95a541af21d3bda84b933f3ee4a9ad2c992a93",
        "font-size.xs": "5f7f27ff9acc4c5964663b80e59fd18bd53728c3",
        "font-size.sm": "ec5f68c497fb3b65db5bd5f44a510a982c44343f",
        "font-size.md": "5cd27acd57be2ece52dfcbb1a5adf81f46cc6e60",
        "font-size.lg": "579a1240f28b953c8520f9444d9c59b614f16ed0",
        "font-size.xl": "b99ab4436993be499f7783340bf9c45554151d25",
        "line-height.3xs": "2e19ab800ebf735045e8aab83975c359ca69b44b",
        "line-height.2xs": "a4d4a08529deaa496f246af6aafc58939b5467a7",
        "line-height.xs": "cc7f86aa0f7f7cd69781ccff767941bb7ce3ce34",
        "line-height.sm": "8a1c66e710bdf719203caee657de6dd00c8b9990",
        "line-height.md": "c4e67129630afcd71c4d4ff188c8cb70fb330b66",
        "line-height.lg": "5b696954125ce6b9561ff981a4213b4ddd23cba4",
        "line-height.xl": "5a281b31c4798338c35cedb138432390b1e176bd"
      },
      "$figmaModeId": "14:19",
      "$figmaCollectionId": "VariableCollectionId:14:349"
    },
    {
      "id": "theme-colors-light",
      "name": "light",
      "group": "theme-colors",
      "selectedTokenSets": {
        "theme-colors/light": "enabled"
      },
      "$figmaStyleReferences": {},
      "$figmaVariableReferences": {
        "text.body": "0d7023684758de47468bcda445b628a32745037d",
        "text.muted": "5e86ae0c244380be4bb9e7598f03c7a93320ffaa",
        "text.extramuted": "b35ec277cc3aafb0a65e1ec5728ebd2070bd3213",
        "text.primary": "f0b0225ce966c6dea7e60a153f2dbb0e51c267e8",
        "background.default": "358e062d1db36ea325edf15365431c550c784722",
        "background.muted": "b6505975efb4368a95b39bc1865a4b8d2e9f960c",
        "background.bg-primary": "2e45297dd7cc601e151d062a93439d991f15f1a6",
        "background.bg-primary-subtle": "83376db791ed1235700a7907b98651abe799b55f"
      },
      "$figmaModeId": "14:20",
      "$figmaCollectionId": "VariableCollectionId:14:350"
    },
    {
      "id": "theme-colors-dark",
      "name": "dark",
      "group": "theme-colors",
      "selectedTokenSets": {
        "theme-colors/dark": "enabled"
      },
      "$figmaStyleReferences": {},
      "$figmaVariableReferences": {
        "text.body": "0d7023684758de47468bcda445b628a32745037d",
        "text.muted": "5e86ae0c244380be4bb9e7598f03c7a93320ffaa",
        "text.extramuted": "b35ec277cc3aafb0a65e1ec5728ebd2070bd3213",
        "text.primary": "f0b0225ce966c6dea7e60a153f2dbb0e51c267e8",
        "background.default": "358e062d1db36ea325edf15365431c550c784722",
        "background.muted": "b6505975efb4368a95b39bc1865a4b8d2e9f960c",
        "background.bg-primary": "2e45297dd7cc601e151d062a93439d991f15f1a6",
        "background.bg-primary-subtle": "83376db791ed1235700a7907b98651abe799b55f"
      },
      "$figmaModeId": "14:21",
      "$figmaCollectionId": "VariableCollectionId:14:350"
    },
    {
      "id": "input-xs",
      "name": "xs",
      "group": "input",
      "selectedTokenSets": {
        "input/xs": "enabled"
      },
      "$figmaStyleReferences": {},
      "$figmaVariableReferences": {
        "input-size": "8043c7f554952ce76e2ae36d04d0b7e41d4de7de",
        "input-radius": "6b700e1f935ff6460575b9da5e8f945d93c06704",
        "input-x-padding": "619b24dbfc228bad14a6b4bd97146bc98daa6183",
        "input-x-gap": "46b7586567bc301884c53b5f374dd34f47818b7f",
        "input-text-size": "430fb4f6850e2c31ac325a4e6bf7913a743e1384",
        "input-line-height": "1025efbe02355ae8a5158e32fe7a7e53b9e68b04"
      },
      "$figmaModeId": "14:22",
      "$figmaCollectionId": "VariableCollectionId:14:351"
    },
    {
      "id": "input-sm",
      "name": "sm",
      "group": "input",
      "selectedTokenSets": {
        "input/sm": "enabled"
      },
      "$figmaStyleReferences": {},
      "$figmaVariableReferences": {
        "input-size": "8043c7f554952ce76e2ae36d04d0b7e41d4de7de",
        "input-radius": "6b700e1f935ff6460575b9da5e8f945d93c06704",
        "input-x-padding": "619b24dbfc228bad14a6b4bd97146bc98daa6183",
        "input-x-gap": "46b7586567bc301884c53b5f374dd34f47818b7f",
        "input-text-size": "430fb4f6850e2c31ac325a4e6bf7913a743e1384",
        "input-line-height": "1025efbe02355ae8a5158e32fe7a7e53b9e68b04"
      },
      "$figmaModeId": "14:23",
      "$figmaCollectionId": "VariableCollectionId:14:351"
    },
    {
      "id": "input-md",
      "name": "md",
      "group": "input",
      "selectedTokenSets": {
        "input/md": "enabled"
      },
      "$figmaStyleReferences": {},
      "$figmaVariableReferences": {
        "input-size": "8043c7f554952ce76e2ae36d04d0b7e41d4de7de",
        "input-radius": "6b700e1f935ff6460575b9da5e8f945d93c06704",
        "input-x-padding": "619b24dbfc228bad14a6b4bd97146bc98daa6183",
        "input-x-gap": "46b7586567bc301884c53b5f374dd34f47818b7f",
        "input-text-size": "430fb4f6850e2c31ac325a4e6bf7913a743e1384",
        "input-line-height": "1025efbe02355ae8a5158e32fe7a7e53b9e68b04"
      },
      "$figmaModeId": "14:24",
      "$figmaCollectionId": "VariableCollectionId:14:351"
    },
    {
      "id": "input-lg",
      "name": "lg",
      "group": "input",
      "selectedTokenSets": {
        "input/lg": "enabled"
      },
      "$figmaStyleReferences": {},
      "$figmaVariableReferences": {
        "input-size": "8043c7f554952ce76e2ae36d04d0b7e41d4de7de",
        "input-radius": "6b700e1f935ff6460575b9da5e8f945d93c06704",
        "input-x-padding": "619b24dbfc228bad14a6b4bd97146bc98daa6183",
        "input-x-gap": "46b7586567bc301884c53b5f374dd34f47818b7f",
        "input-text-size": "430fb4f6850e2c31ac325a4e6bf7913a743e1384",
        "input-line-height": "1025efbe02355ae8a5158e32fe7a7e53b9e68b04"
      },
      "$figmaModeId": "14:25",
      "$figmaCollectionId": "VariableCollectionId:14:351"
    }
  ],
  "$metadata": {
    "tokenSetOrder": [
      "global/variables",
      "theme-colors/light",
      "theme-colors/dark",
      "input/xs",
      "input/sm",
      "input/md",
      "input/lg"
    ]
  }
}